{
  "slug": "game-software",
  "name": "ゲーム",
  "updatedAt": "2026-04-09",
  "products": [
    {
      "rank": 1,
      "asin": "B09998GN7Z",
      "title": "ニンテンドープリペイド番号 2000円|オンラインコード版",
      "image": "https://m.media-amazon.com/images/I/31ZbHYEeb6S._SL500_.jpg",
      "affiliateUrl": "https://www.amazon.co.jp/dp/B09998GN7Z/?tag=amazonrankingbest-22",
      "price": "￥2,000",
      "description": null,
      "badge": "1位",
      "rating": null,
      "reviewCount": null,
      "updatedAt": "2026-04-09"
    },
    {
      "rank": 2,
      "asin": "B09997WD23",
      "title": "ニンテンドープリペイド番号 500円|オンラインコード版",
      "image": "https://m.media-amazon.com/images/I/317Q5yalUYS._SL500_.jpg",
      "affiliateUrl": "https://www.amazon.co.jp/dp/B09997WD23/?tag=amazonrankingbest-22",
      "price": "￥500",
      "description": null,
      "badge": null,
      "rating": null,
      "reviewCount": null,
      "updatedAt": "2026-04-09"
    },
    {
      "rank": 3,
      "asin": "B0F1CJB2Q5",
      "title": "ベルモンド Switch2 / スイッチ2 用 保護フィルム 【2枚セット+簡単ガイド枠付き】ガラスフィルム | 全面保護 ピッタリサイズ 硬度 10H 貼りやすい ガイド付き ギフト プレゼント | モンスターフィルム B1510",
      "image": "https://m.media-amazon.com/images/I/51TUgj0aCWL._SL500_.jpg",
      "affiliateUrl": "https://www.amazon.co.jp/dp/B0F1CJB2Q5/?tag=amazonrankingbest-22",
      "price": "￥1,598",
      "description": null,
      "badge": null,
      "rating": null,
      "reviewCount": null,
      "updatedAt": "2026-04-09"
    },
    {
      "rank": 4,
      "asin": "B084HPGQ9W",
      "title": "あつまれ どうぶつの森 -Switch",
      "image": "https://m.media-amazon.com/images/I/51JWLmoGY3L._SL500_.jpg",
      "affiliateUrl": "https://www.amazon.co.jp/dp/B084HPGQ9W/?tag=amazonrankingbest-22",
      "price": "￥5,545",
      "description": null,
      "badge": null,
      "rating": null,
      "reviewCount": null,
      "updatedAt": "2026-04-09"
    },
    {
      "rank": 5,
      "asin": "B09999M8HV",
      "title": "ニンテンドープリペイド番号 1000円|オンラインコード版",
      "image": "https://m.media-amazon.com/images/I/41KlY5A6LAL._SL500_.jpg",
      "affiliateUrl": "https://www.amazon.co.jp/dp/B09999M8HV/?tag=amazonrankingbest-22",
      "price": "￥1,000",
      "description": null,
      "badge": null,
      "rating": null,
      "reviewCount": null,
      "updatedAt": "2026-04-09"
    },
    {
      "rank": 6,
      "asin": "B09996CH6H",
      "title": "ニンテンドープリペイド番号 3000円|オンラインコード版",
      "image": "https://m.media-amazon.com/images/I/31J40WR0EQS._SL500_.jpg",
      "affiliateUrl": "https://www.amazon.co.jp/dp/B09996CH6H/?tag=amazonrankingbest-22",
      "price": "￥3,000",
      "description": null,
      "badge": null,
      "rating": null,
      "reviewCount": null,
      "updatedAt": "2026-04-09"
    },
    {
      "rank": 7,
      "asin": "B0GS53CT4G",
      "title": "Nintendo Switch 2(日本語・国内専用)＋ぽこ あ ポケモン|オンラインコード版",
      "image": "https://m.media-amazon.com/images/I/41ZmGbb-H1L._SL500_.jpg",
      "affiliateUrl": "https://www.amazon.co.jp/dp/B0GS53CT4G/?tag=amazonrankingbest-22",
      "price": "￥57,327",
      "description": null,
      "badge": null,
      "rating": null,
      "reviewCount": null,
      "updatedAt": "2026-04-09"
    },
    {
      "rank": 8,
      "asin": "B07FDW61HX",
      "title": "大乱闘スマッシュブラザーズ SPECIAL - Switch",
      "image": "https://m.media-amazon.com/images/I/51u857BI90L._SL500_.jpg",
      "affiliateUrl": "https://www.amazon.co.jp/dp/B07FDW61HX/?tag=amazonrankingbest-22",
      "price": "￥6,473",
      "description": null,
      "badge": null,
      "rating": null,
      "reviewCount": null,
      "updatedAt": "2026-04-09"
    },
    {
      "rank": 9,
      "asin": "B07D131MS4",
      "title": "Minecraft (マインクラフト) - Switch",
      "image": "https://m.media-amazon.com/images/I/41Hhzgz71KL._SL500_.jpg",
      "affiliateUrl": "https://www.amazon.co.jp/dp/B07D131MS4/?tag=amazonrankingbest-22",
      "price": "￥3,400",
      "description": null,
      "badge": null,
      "rating": null,
      "reviewCount": null,
      "updatedAt": "2026-04-09"
    },
    {
      "rank": 10,
      "asin": "B0FYNV2H19",
      "title": "あつまれ どうぶつの森 Nintendo Switch 2 Edition -Switch2",
      "image": "https://m.media-amazon.com/images/I/51r1u0GK3UL._SL500_.jpg",
      "affiliateUrl": "https://www.amazon.co.jp/dp/B0FYNV2H19/?tag=amazonrankingbest-22",
      "price": "￥6,155",
      "description": null,
      "badge": null,
      "rating": null,
      "reviewCount": null,
      "updatedAt": "2026-04-09"
    },
    {
      "rank": 11,
      "asin": "B0BJ1SSV1P",
      "title": "SteelSeries ラピッドトリガー 搭載 ゲーミングキーボード テンキーレス 有線 日本語配列 OmniPointスイッチ 有機ELディスプレイ搭載 Apex Pro TKL (2023) 64861 ブラック",
      "image": "https://m.media-amazon.com/images/I/41X-Go8gMFL._SL500_.jpg",
      "affiliateUrl": "https://www.amazon.co.jp/dp/B0BJ1SSV1P/?tag=amazonrankingbest-22",
      "price": "￥21,980",
      "description": null,
      "badge": null,
      "rating": null,
      "reviewCount": null,
      "updatedAt": "2026-04-09"
    },
    {
      "rank": 12,
      "asin": "B08F7S4YG9",
      "title": "Razer BlackShark V2 X ゲーミングヘッドセット 3.5mmアナログ 7.1ch サラウンド 特許技術採用50mmドライバー 単一指向性マイク ノイズキャンセリング 高遮音性イヤーカップ 軽量240g PC PS4 PS5 Xbox Nintendo Switch 【日本正規代理店保証品】 RZ04-03240100-R3M1",
      "image": "https://m.media-amazon.com/images/I/31O0MHETF-L._SL500_.jpg",
      "affiliateUrl": "https://www.amazon.co.jp/dp/B08F7S4YG9/?tag=amazonrankingbest-22",
      "price": "￥5,490",
      "description": null,
      "badge": null,
      "rating": null,
      "reviewCount": null,
      "updatedAt": "2026-04-09"
    },
    {
      "rank": 13,
      "asin": "B097DBSJ1F",
      "title": "Logicool G ゲーミングヘッドセット G335 ゲーミング ヘッドセット G335BK 軽量 222g 3.5mm 有線 立体音響 ステレオ 2.1ch フリップミュート マイク付き PS5 PS4 PC Switch 2 Xbox スマホ 対応 ヘッドホン ヘッドフォン ブラック 国内正規品",
      "image": "https://m.media-amazon.com/images/I/41NVI9RUgkS._SL500_.jpg",
      "affiliateUrl": "https://www.amazon.co.jp/dp/B097DBSJ1F/?tag=amazonrankingbest-22",
      "price": "￥7,250",
      "description": null,
      "badge": null,
      "rating": null,
      "reviewCount": null,
      "updatedAt": "2026-04-09"
    },
    {
      "rank": 14,
      "asin": "B0F1XLZG8G",
      "title": "Switch 2 コントローラー ダブルホール機能 Switch1/2代对応【2025革新モデル】スイッチ プロコン TURBO自動連射機能 6軸ジャイロセンサー搭載 4階段HD振動 背面ボタン付き 9色RGBライト ゼロ遅延 無線接続 1000mAh大容量 Bluetooth 人間工学デザイン Switch全世代に対応/PC/Android/iOSにも対応 日本語取扱説明書付き (Black)",
      "image": "https://m.media-amazon.com/images/I/51YOYvs5N-L._SL500_.jpg",
      "affiliateUrl": "https://www.amazon.co.jp/dp/B0F1XLZG8G/?tag=amazonrankingbest-22",
      "price": "￥3,199",
      "description": null,
      "badge": null,
      "rating": null,
      "reviewCount": null,
      "updatedAt": "2026-04-09"
    },
    {
      "rank": 15,
      "asin": "B0DWWSRTWP",
      "title": "Haute42 アケコン レバーレス　レバーレスコントローラー T16 PROブラック ファイトスティック PC用ジョイスティック ボタン静音強め 押し心地絶秒 スリムで天板広め EVO For PC Switch2 Switch PS4 PS3等に対応 膝置き可 無遅延 レバーレス コントローラー TYPE-C RGB LED ホットスワップ 向け アーケートコントローラー アーケードスティック 連射機能",
      "image": "https://m.media-amazon.com/images/I/31aYmM8wcKL._SL500_.jpg",
      "affiliateUrl": "https://www.amazon.co.jp/dp/B0DWWSRTWP/?tag=amazonrankingbest-22",
      "price": "￥9,998",
      "description": null,
      "badge": null,
      "rating": null,
      "reviewCount": null,
      "updatedAt": "2026-04-09"
    },
    {
      "rank": 16,
      "asin": "B0C3BV19Q3",
      "title": "ハイパーエックス(HyperX) HyperX Cloud III  ゲーミングヘッドセット DTS Headphone:X空間オーディオ 53mmドライバー搭載 Cloud IIの 快適性 ブラック-レッド PC、PS5、PS4、Xboxシリーズ、Nintendo Switch、モバイル727A9AA",
      "image": "https://m.media-amazon.com/images/I/41x-edlmYSL._SL500_.jpg",
      "affiliateUrl": "https://www.amazon.co.jp/dp/B0C3BV19Q3/?tag=amazonrankingbest-22",
      "price": "￥12,980",
      "description": null,
      "badge": null,
      "rating": null,
      "reviewCount": null,
      "updatedAt": "2026-04-09"
    },
    {
      "rank": 17,
      "asin": "B0C3BSZ56D",
      "title": "ハイパーエックス(HyperX) HyperX Cloud III  ゲーミングヘッドセット DTS Headphone:X空間オーディオ 53mmドライバー搭載 Cloud IIの 快適性 ブラック PC、PS5、PS4、Xboxシリーズ、Nintendo Switch、モバイル727A8AA",
      "image": "https://m.media-amazon.com/images/I/31KNREE3rcL._SL500_.jpg",
      "affiliateUrl": "https://www.amazon.co.jp/dp/B0C3BSZ56D/?tag=amazonrankingbest-22",
      "price": "￥12,980",
      "description": null,
      "badge": null,
      "rating": null,
      "reviewCount": null,
      "updatedAt": "2026-04-09"
    },
    {
      "rank": 18,
      "asin": "B0FDQMP4RW",
      "title": "Haute42 レバーレス アケコン レバーレスコントローラー C16ブラック 自由度と性能を両立 磁石式着脱 膝置き可 ライトロック＆大会試合ロック PC Switch2 Switch PS4 PS3など対応 静音強化 絶妙押し心地 無遅延 スリム薄型 広天板 耐久性 DIY アンビエントLED 天板カスタマイズ自由 ホットスワップ",
      "image": "https://m.media-amazon.com/images/I/51Mn9URy9PL._SL500_.jpg",
      "affiliateUrl": "https://www.amazon.co.jp/dp/B0FDQMP4RW/?tag=amazonrankingbest-22",
      "price": "￥12,399",
      "description": null,
      "badge": null,
      "rating": null,
      "reviewCount": null,
      "updatedAt": "2026-04-09"
    },
    {
      "rank": 19,
      "asin": "B0DY5X1659",
      "title": "XPT コントローラー ゲームパッド Switch2 Switch pc xbox iOS Android windows スマホ対応 小さいサイズ ミニ 超軽量 Turbo 6軸ジャイロセンサー Bluetooth 無線 有線 スティック収納可 18時間連続使用 (ブラック)",
      "image": "https://m.media-amazon.com/images/I/319fMb7BhCL._SL500_.jpg",
      "affiliateUrl": "https://www.amazon.co.jp/dp/B0DY5X1659/?tag=amazonrankingbest-22",
      "price": "￥3,134",
      "description": null,
      "badge": null,
      "rating": null,
      "reviewCount": null,
      "updatedAt": "2026-04-09"
    },
    {
      "rank": 20,
      "asin": "B0DFXWJ2PT",
      "title": "Haute42 アケコン レバーレス コントローラー レバーレス アケコン ボタン枠の追加 極薄の厚さ 天板広め ボタンが外れずに 膝置き可 U16黒 格ゲー向け For PC Switch2 Switch PS4 PS3 持ち運び便利 無遅延 コンパクト RGB LED ホットスワップ ボタン交換可能 適度なボタン間隔 連射機能 日本語説明書 (U16 ブラック)",
      "image": "https://m.media-amazon.com/images/I/41RXnSGtjKL._SL500_.jpg",
      "affiliateUrl": "https://www.amazon.co.jp/dp/B0DFXWJ2PT/?tag=amazonrankingbest-22",
      "price": "￥10,499",
      "description": null,
      "badge": null,
      "rating": null,
      "reviewCount": null,
      "updatedAt": "2026-04-09"
    }
  ]
}