{
  "slug": "smartphone",
  "name": "スマートフォン",
  "updatedAt": "2026-03-25",
  "products": [
    {
      "rank": 1,
      "asin": "B0FQG91G3M",
      "title": "Apple iPhone 17 256GB (SIMフリー)：ProMotionを採用した6.3インチディスプレイ、A19チップ、グループセルフィーを一段とスマートに撮れるセンターフレームフロントカメラ、向上した耐擦傷性能、一日中使えるバッテリー；ミストブルー",
      "image": "https://m.media-amazon.com/images/I/31gixf8svoL._SL500_.jpg",
      "affiliateUrl": "https://www.amazon.co.jp/dp/B0FQG91G3M/?tag=amazonrankingbest-22",
      "price": null,
      "description": null,
      "badge": "1位",
      "updatedAt": "2026-03-25"
    },
    {
      "rank": 2,
      "asin": "B0GQVJ1CPB",
      "title": "Apple iPhone 17e 512GB：6.1インチSuper Retina XDRディスプレイ、A19チップ、一日中使えるバッテリー、48MP Fusionカメラ、最小ストレージ512GB；ホワイト",
      "image": "https://m.media-amazon.com/images/I/3105OdFE4kL._SL500_.jpg",
      "affiliateUrl": "https://www.amazon.co.jp/dp/B0GQVJ1CPB/?tag=amazonrankingbest-22",
      "price": null,
      "description": null,
      "badge": null,
      "updatedAt": "2026-03-25"
    },
    {
      "rank": 3,
      "asin": "B0BBLYSD9J",
      "title": "【整備済み品】 Apple iPhone SE（第3世代） 128GB スターライト SIMフリー (整備済み品)",
      "image": "https://m.media-amazon.com/images/I/31gI87Wc46L._SL500_.jpg",
      "affiliateUrl": "https://www.amazon.co.jp/dp/B0BBLYSD9J/?tag=amazonrankingbest-22",
      "price": null,
      "description": null,
      "badge": null,
      "updatedAt": "2026-03-25"
    },
    {
      "rank": 4,
      "asin": "B0FDKVB871",
      "title": "Motorola(モトローラ)motorola g66j 5G PANTONE｜8GB/128GB｜ブラックオイスター｜SIMフリースマホ本体端末｜NFC/FeliCa対応｜FMラジオ搭載｜正規代理店品｜6.7インチ｜FHD+｜IP68・IP69防水防塵｜大容量バッテリー5,200mAh｜PB810002JP",
      "image": "https://m.media-amazon.com/images/I/31WGhTrYRjL._SL500_.jpg",
      "affiliateUrl": "https://www.amazon.co.jp/dp/B0FDKVB871/?tag=amazonrankingbest-22",
      "price": null,
      "description": null,
      "badge": null,
      "updatedAt": "2026-03-25"
    },
    {
      "rank": 5,
      "asin": "B0BLY4F4WM",
      "title": "【整備済み品】 Apple iPhone 14 128GB スターライト SIMフリー 5G対応 (整備済み品)",
      "image": "https://m.media-amazon.com/images/I/3144jXPtX4L._SL500_.jpg",
      "affiliateUrl": "https://www.amazon.co.jp/dp/B0BLY4F4WM/?tag=amazonrankingbest-22",
      "price": null,
      "description": null,
      "badge": null,
      "updatedAt": "2026-03-25"
    },
    {
      "rank": 6,
      "asin": "B0DYJSQ5K5",
      "title": "Motorola(モトローラ)motog05|8GB/128GB|ミスティブルー|SIMフリースマホ本体端末|NFC対応|ヴィーガンレザー|ゴリラガラス|正規代理店品|6.7インチ|HD+|IP52防水防塵|大容量バッテリー5,200mAh|RAMブースト機能|PB6N0003JP",
      "image": "https://m.media-amazon.com/images/I/41lYNFQfPxL._SL500_.jpg",
      "affiliateUrl": "https://www.amazon.co.jp/dp/B0DYJSQ5K5/?tag=amazonrankingbest-22",
      "price": null,
      "description": null,
      "badge": null,
      "updatedAt": "2026-03-25"
    },
    {
      "rank": 7,
      "asin": "B0GK8DRT2N",
      "title": "Xiaomi POCO X8 Pro Max 12GB+256GB日本語版 8500mAhバッテリー Dimensity 9500s 100Wハイパーチャージ IceLoop冷却システム 6.83インチ 1.5K解像度 120Hz有機ディスプレイ IP68防塵・防水 docomo/au/SoftBank/Rakuten Mobile 回線対応 Simフリー スマートフォン ブラック",
      "image": "https://m.media-amazon.com/images/I/31k7hZARsWL._SL500_.jpg",
      "affiliateUrl": "https://www.amazon.co.jp/dp/B0GK8DRT2N/?tag=amazonrankingbest-22",
      "price": null,
      "description": null,
      "badge": null,
      "updatedAt": "2026-03-25"
    },
    {
      "rank": 8,
      "asin": "B0GK98Z3GP",
      "title": "Samsung Galaxy S26 Ultra 256GB｜ブラック｜Galaxy AI対応｜SIMフリースマホ 本体 端末｜FeliCa対応｜Samsung純正 国内正規品｜6.9インチ｜軽量約214g｜IP68防水防塵｜QHD+｜バッテリー 5,000mAh｜SM-S948QZKASJP",
      "image": "https://m.media-amazon.com/images/I/41643Tv7VSL._SL500_.jpg",
      "affiliateUrl": "https://www.amazon.co.jp/dp/B0GK98Z3GP/?tag=amazonrankingbest-22",
      "price": null,
      "description": null,
      "badge": null,
      "updatedAt": "2026-03-25"
    },
    {
      "rank": 9,
      "asin": "B0GK96HVP1",
      "title": "Samsung Galaxy S26 256GB｜ブラック｜Galaxy AI対応｜SIMフリースマホ 本体 端末｜FeliCa対応｜Samsung純正 国内正規品｜6.3インチ｜軽量約167g｜IP68防水防塵｜フルHD+｜バッテリー 4,300mAh｜SM-S942QZKESJP",
      "image": "https://m.media-amazon.com/images/I/31lTk9L7A7L._SL500_.jpg",
      "affiliateUrl": "https://www.amazon.co.jp/dp/B0GK96HVP1/?tag=amazonrankingbest-22",
      "price": null,
      "description": null,
      "badge": null,
      "updatedAt": "2026-03-25"
    },
    {
      "rank": 10,
      "asin": "B0CMWN58CX",
      "title": "【整備済み品】 Apple iPhone 15 128GB ブラック SIMフリー 5G対応 (整備済み品)",
      "image": "https://m.media-amazon.com/images/I/31KxpX7Xk7L._SL500_.jpg",
      "affiliateUrl": "https://www.amazon.co.jp/dp/B0CMWN58CX/?tag=amazonrankingbest-22",
      "price": null,
      "description": null,
      "badge": null,
      "updatedAt": "2026-03-25"
    },
    {
      "rank": 11,
      "asin": "B09P7ZWQM9",
      "title": "【整備済み品】 Apple iPhone 13 mini 128GB ミッドナイト SIMフリー (整備済み品)",
      "image": "https://m.media-amazon.com/images/I/313Cr5YsOIL._SL500_.jpg",
      "affiliateUrl": "https://www.amazon.co.jp/dp/B09P7ZWQM9/?tag=amazonrankingbest-22",
      "price": null,
      "description": null,
      "badge": null,
      "updatedAt": "2026-03-25"
    },
    {
      "rank": 12,
      "asin": "B086ZTPCC5",
      "title": "ASUS Chromebook クロームブック Detachable CM30 10.5インチ 2in1 タブレット 日本語キーボード 8GBメモリ 重量609g ペン付き フォグシルバー CM3001DM2A-R70006/A",
      "image": "https://m.media-amazon.com/images/I/41Qz9NJfwaL._SL500_.jpg",
      "affiliateUrl": "https://www.amazon.co.jp/dp/B086ZTPCC5/?tag=amazonrankingbest-22",
      "price": null,
      "description": null,
      "badge": null,
      "updatedAt": "2026-03-25"
    },
    {
      "rank": 13,
      "asin": "B08N6LJ71W",
      "title": "Xiaomi POCO F7 12GB+256GB 日本語版 Simフリー スマートフォン Snapdragon 8s Gen 4を搭載 6500mAh 6.83インチ 高精細ディスプレイ 90Wハイパーチャージ docomo/au/SoftBank/Rakuten Mobile 回線対応 シルバー",
      "image": "https://m.media-amazon.com/images/I/41G689II29L._SL500_.jpg",
      "affiliateUrl": "https://www.amazon.co.jp/dp/B08N6LJ71W/?tag=amazonrankingbest-22",
      "price": null,
      "description": null,
      "badge": null,
      "updatedAt": "2026-03-25"
    },
    {
      "rank": 14,
      "asin": "B0F535RF9Z",
      "title": "Google Pixel 9a 128GB+8GB SIMフリー [Obsidian] * SIM FREE スマートフォン",
      "image": "https://m.media-amazon.com/images/I/31gI-U4GtcL._SL500_.jpg",
      "affiliateUrl": "https://www.amazon.co.jp/dp/B0F535RF9Z/?tag=amazonrankingbest-22",
      "price": null,
      "description": null,
      "badge": null,
      "updatedAt": "2026-03-25"
    },
    {
      "rank": 15,
      "asin": "B0928LQ3Z7",
      "title": "【整備済み品】 Apple iPhone 12 mini 128GB ブルー SIMフリー (整備済み品)",
      "image": "https://m.media-amazon.com/images/I/41mgelHPttL._SL500_.jpg",
      "affiliateUrl": "https://www.amazon.co.jp/dp/B0928LQ3Z7/?tag=amazonrankingbest-22",
      "price": null,
      "description": null,
      "badge": null,
      "updatedAt": "2026-03-25"
    },
    {
      "rank": 16,
      "asin": "B0GK86D2SY",
      "title": "Xiaomi POCO X8 Pro 8GB+256GB 日本語版 Dimensity 8500-Ultra 6500mAh大容量バッテリー 100Wハイパーチャージ IceLoop冷却システム 6.59インチ 1.5K解像度 120Hz 有機ディスプレイ IP68防塵・防水docomo/au/SoftBank/Rakuten Mobile 回線対応 Simフリー スマートフォンブラック",
      "image": "https://m.media-amazon.com/images/I/31HvyJRvCRL._SL500_.jpg",
      "affiliateUrl": "https://www.amazon.co.jp/dp/B0GK86D2SY/?tag=amazonrankingbest-22",
      "price": null,
      "description": null,
      "badge": null,
      "updatedAt": "2026-03-25"
    },
    {
      "rank": 17,
      "asin": "B0G2KS41PJ",
      "title": "シャオミ(Xiaomi) SIMフリースマートフォン REDMI 15 5G 8+256GB 7000mAh 大容量バッテリー 33Wチャージ 5G対応 6.9インチFHD NFC/FeliCa対応 Snapdragon 6s Gen3 5000万画素AIカメラ IP64防滴防塵 docomo/au/SoftBank/Rakuten Mobile 回線対応ミッドナイトブラック",
      "image": "https://m.media-amazon.com/images/I/31Rwis15A+L._SL500_.jpg",
      "affiliateUrl": "https://www.amazon.co.jp/dp/B0G2KS41PJ/?tag=amazonrankingbest-22",
      "price": null,
      "description": null,
      "badge": null,
      "updatedAt": "2026-03-25"
    },
    {
      "rank": 18,
      "asin": "B0DSN5MDZT",
      "title": "Xiaomi POCO X7 Pro 8GB+256GB 日本語版 Simフリー スマートフォン 90Wハイパーチャージ 120Hz 有機ELディスプレイ IP68防塵・防水 docomo/au/SoftBank/Rakuten Mobile 回線対応 ブラック",
      "image": "https://m.media-amazon.com/images/I/31UKCUCgOrL._SL500_.jpg",
      "affiliateUrl": "https://www.amazon.co.jp/dp/B0DSN5MDZT/?tag=amazonrankingbest-22",
      "price": null,
      "description": null,
      "badge": null,
      "updatedAt": "2026-03-25"
    },
    {
      "rank": 19,
      "asin": "B09P82T3PZ",
      "title": "【整備済み品】 Apple iPhone 13 128GB スターライト SIMフリー (整備済み品)",
      "image": "https://m.media-amazon.com/images/I/31EDsZC0G+L._SL500_.jpg",
      "affiliateUrl": "https://www.amazon.co.jp/dp/B09P82T3PZ/?tag=amazonrankingbest-22",
      "price": null,
      "description": null,
      "badge": null,
      "updatedAt": "2026-03-25"
    },
    {
      "rank": 20,
      "asin": "B0FJXY48HP",
      "title": "arrows(アローズ) Alpha【正規代理店】SIMフリー スマートフォン スマホ 本体 大画面 大容量バッテリー メモリ12GB ストレージ512GB 6.4インチ USB Type-C 超急速充電 防水 除菌 (ホワイト)",
      "image": "https://m.media-amazon.com/images/I/415ta7KG-dL._SL500_.jpg",
      "affiliateUrl": "https://www.amazon.co.jp/dp/B0FJXY48HP/?tag=amazonrankingbest-22",
      "price": null,
      "description": null,
      "badge": null,
      "updatedAt": "2026-03-25"
    }
  ]
}