{
  "_comment": "ASIN をキーに rating（1〜5）と comment を設定してください。コミットすると自動反映されます。",
  "B0FZPRPVKC": {
    "rating": 5,
    "comment": "Switch2と同時に買うなら迷わずこれ！発売直後から品薄が続いている注目作です。"
  },
  "B0DX1BC3R8": {
    "rating": 5,
    "comment": "Switch2本体。後継機とあって処理性能が別格。久しぶりにゲームを再開したい大人にも最高の一台。"
  },
  "B0GR6F619Z": {
    "rating": 5,
    "comment": "M4チップの性能は体感で別次元。動画編集やコーディングのサブ機として最強クラス。"
  },
  "B0DYF82545": {
    "rating": 4,
    "comment": "今この価格でスマートウォッチが手に入る時代です。Xiaomiのコスパはエグすぎます。"
  },
  "B0GJSCGFTP": {
    "rating": 4,
    "comment": "いろいろ言われがちなメーカですが、技術力は世界トップレベル。製品としては素晴らしいです。"
  },
  "B0FNMP8LZX": {
    "rating": 5,
    "comment": "DJIは強い。初めてのアクションカメラなら2026年3月時点ではこれが最強です。個人的にデザインはinsta360の方が好きです。"
  },
  "B0GN36R863": {
    "rating": 5,
    "comment": "日本で唯一になってしまったApple製品情報誌もいよいよ紙媒体では廃刊となります。有終の美を飾る2026年5月号はぜひ紙媒体で家宝にしましょう！"
  },
  "B0FQFPJCW1": {
    "rating": 5,
    "comment": "ProユースではないiPhoneの完成形ともいえるのがこのiPhone 17です。世界的に見ても日本は安く売られているので海外に流れがち。買えるなら即Goです。"
  },
  "B0GQVTTNQW": {
    "rating": 4,
    "comment": "iPhone 16eで搭載が見送られたMagSafeがついに搭載。10万を切る価格帯、無印iPhoneはまだ高いという方はiPhone 17eがベストチョイスです。"
  },
  "B0BBLWS333": {
    "rating": 4,
    "comment": "実質最後のSEとなる本機。大きすぎないサイズ感、ホームボタンが安心する方はこちら。整備済みとはいえこの価格は買いです。サブ機にもおすすめ！"
  }
}
